{"id": "a4jZzlWofAY", "title": "Stop Buying Nintendo Games. Stop Buying Nintendo Consoles. Stop Buying Joy-Cons.", "formats": [{"asr": 22050, "filesize": 838909, "format_id": "139", "format_note": "low", "source_preference": -1, "quality": 2, "tbr": 48.822, "url": "https://rr1---sn-npoeeney.googlevideo.com/videoplayback?expire=1658282174&ei=XgzXYu6tJ42YvwSvr5u4Dg&ip=2400%3A6180%3A0%3Ad0%3A%3Ad34%3Af001&id=o-AIzsJMYjBr9VLOtvgvW4TdPQKyvORN71gpt6S31ZPFHJ&itag=139&source=youtube&requiressl=yes&mh=6v&mm=31%2C29&mn=sn-npoeeney%2Csn-npoe7nz7&ms=au%2Crdu&mv=m&mvi=1&pl=62&initcwndbps=327500&vprv=1&mime=audio%2Fmp4&gir=yes&clen=838909&dur=137.462&lmt=1638076977394905&mt=1658260164&fvip=5&keepalive=yes&fexp=24001373%2C24007246&c=ANDROID&txp=6311224&sparams=expire%2Cei%2Cip%2Cid%2Citag%2Csource%2Crequiressl%2Cvprv%2Cmime%2Cgir%2Cclen%2Cdur%2Clmt&sig=AOq0QJ8wRgIhANDObtMfRKW51VaGXAWcbZLwhzd1gsU5KAMUXiTshmlWAiEAyJxKKrJTTpRVCCHxZU5CiTCm-dSRW728RcfbauYTuKw%3D&lsparams=mh%2Cmm%2Cmn%2Cms%2Cmv%2Cmvi%2Cpl%2Cinitcwndbps&lsig=AG3C_xAwRQIhAMkoUZjnSdxpJTiW9eM1ymLyQUoJq5t-EQGG3FCqKL-AAiB7PmkktX6Px-fhcgidlMnowNIvOtV9tgaAmZnSCr2zog%3D%3D", "language": "", "language_preference": -1, "ext": "m4a", "vcodec": "none", "acodec": "mp4a.40.5", "abr": 48.822, "downloader_options": {"http_chunk_size": 10485760}, "container": "m4a_dash", "protocol": "https", "audio_ext": "m4a", "video_ext": "none", "format": "139 - audio only (low)", "resolution": "audio only", "http_headers": {"User-Agent": "Mozilla/5.0 (Windows NT 10.0; Win64; x64) AppleWebKit/537.36 (KHTML, like Gecko) Chrome/70.0.3533.0 Safari/537.36", "Accept-Charset": "ISO-8859-1,utf-8;q=0.7,*;q=0.7", "Accept": "text/html,application/xhtml+xml,application/xml;q=0.9,*/*;q=0.8", "Accept-Encoding": "gzip, deflate", "Accept-Language": "en-us,en;q=0.5"}}, {"asr": 48000, "filesize": 756772, "format_id": "249", "format_note": "low", "source_preference": -1, "quality": 2, "tbr": 44.081, "url": "https://rr1---sn-npoeeney.googlevideo.com/videoplayback?expire=1658282174&ei=XgzXYu6tJ42YvwSvr5u4Dg&ip=2400%3A6180%3A0%3Ad0%3A%3Ad34%3Af001&id=o-AIzsJMYjBr9VLOtvgvW4TdPQKyvORN71gpt6S31ZPFHJ&itag=249&source=youtube&requiressl=yes&mh=6v&mm=31%2C29&mn=sn-npoeeney%2Csn-npoe7nz7&ms=au%2Crdu&mv=m&mvi=1&pl=62&initcwndbps=327500&vprv=1&mime=audio%2Fwebm&gir=yes&clen=756772&dur=137.341&lmt=1638076995580520&mt=1658260164&fvip=5&keepalive=yes&fexp=24001373%2C24007246&c=ANDROID&txp=6311224&sparams=expire%2Cei%2Cip%2Cid%2Citag%2Csource%2Crequiressl%2Cvprv%2Cmime%2Cgir%2Cclen%2Cdur%2Clmt&sig=AOq0QJ8wRQIgQIiRQK0szMaxdYpYUViEQZ1oGjhC0JNlE5MyP4_EV-ICIQDGOzD0mH22ERczku74SJ6HanSA4si3frxZ7nwjSJFL4A%3D%3D&lsparams=mh%2Cmm%2Cmn%2Cms%2Cmv%2Cmvi%2Cpl%2Cinitcwndbps&lsig=AG3C_xAwRQIhAMkoUZjnSdxpJTiW9eM1ymLyQUoJq5t-EQGG3FCqKL-AAiB7PmkktX6Px-fhcgidlMnowNIvOtV9tgaAmZnSCr2zog%3D%3D", "language": "", "language_preference": -1, "ext": "webm", "vcodec": "none", "acodec": "opus", "abr": 44.081, "downloader_options": {"http_chunk_size": 10485760}, "container": "webm_dash", "protocol": "https", "audio_ext": "webm", "video_ext": "none", "format": "249 - audio only (low)", "resolution": "audio only", "http_headers": {"User-Agent": "Mozilla/5.0 (Windows NT 10.0; Win64; x64) AppleWebKit/537.36 (KHTML, like Gecko) Chrome/70.0.3533.0 Safari/537.36", "Accept-Charset": "ISO-8859-1,utf-8;q=0.7,*;q=0.7", "Accept": "text/html,application/xhtml+xml,application/xml;q=0.9,*/*;q=0.8", "Accept-Encoding": "gzip, deflate", "Accept-Language": "en-us,en;q=0.5"}}, {"asr": 48000, "filesize": 968193, "format_id": "250", "format_note": "low", "source_preference": -1, "quality": 2, "tbr": 56.396, "url": "https://rr1---sn-npoeeney.googlevideo.com/videoplayback?expire=1658282174&ei=XgzXYu6tJ42YvwSvr5u4Dg&ip=2400%3A6180%3A0%3Ad0%3A%3Ad34%3Af001&id=o-AIzsJMYjBr9VLOtvgvW4TdPQKyvORN71gpt6S31ZPFHJ&itag=250&source=youtube&requiressl=yes&mh=6v&mm=31%2C29&mn=sn-npoeeney%2Csn-npoe7nz7&ms=au%2Crdu&mv=m&mvi=1&pl=62&initcwndbps=327500&vprv=1&mime=audio%2Fwebm&gir=yes&clen=968193&dur=137.341&lmt=1638076986451545&mt=1658260164&fvip=5&keepalive=yes&fexp=24001373%2C24007246&c=ANDROID&txp=6311224&sparams=expire%2Cei%2Cip%2Cid%2Citag%2Csource%2Crequiressl%2Cvprv%2Cmime%2Cgir%2Cclen%2Cdur%2Clmt&sig=AOq0QJ8wRAIgB8t3VSBvLEfO8yDyaZW8g4mZR9kLoqqSRkn2OxYPmGkCIDZBSZCW_w2RvRXAZTDRuoWSh_d4k_GbTvI1RKoAMwd-&lsparams=mh%2Cmm%2Cmn%2Cms%2Cmv%2Cmvi%2Cpl%2Cinitcwndbps&lsig=AG3C_xAwRQIhAMkoUZjnSdxpJTiW9eM1ymLyQUoJq5t-EQGG3FCqKL-AAiB7PmkktX6Px-fhcgidlMnowNIvOtV9tgaAmZnSCr2zog%3D%3D", "language": "", "language_preference": -1, "ext": "webm", "vcodec": "none", "acodec": "opus", "abr": 56.396, "downloader_options": {"http_chunk_size": 10485760}, "container": "webm_dash", "protocol": "https", "audio_ext": "webm", "video_ext": "none", "format": "250 - audio only (low)", "resolution": "audio only", "http_headers": {"User-Agent": "Mozilla/5.0 (Windows NT 10.0; Win64; x64) AppleWebKit/537.36 (KHTML, like Gecko) Chrome/70.0.3533.0 Safari/537.36", "Accept-Charset": "ISO-8859-1,utf-8;q=0.7,*;q=0.7", "Accept": "text/html,application/xhtml+xml,application/xml;q=0.9,*/*;q=0.8", "Accept-Encoding": "gzip, deflate", "Accept-Language": "en-us,en;q=0.5"}}, {"asr": 44100, "filesize": 2223860, "format_id": "140", "format_note": "medium", "source_preference": -1, "quality": 3, "tbr": 129.511, "url": "https://rr1---sn-npoeeney.googlevideo.com/videoplayback?expire=1658282174&ei=XgzXYu6tJ42YvwSvr5u4Dg&ip=2400%3A6180%3A0%3Ad0%3A%3Ad34%3Af001&id=o-AIzsJMYjBr9VLOtvgvW4TdPQKyvORN71gpt6S31ZPFHJ&itag=140&source=youtube&requiressl=yes&mh=6v&mm=31%2C29&mn=sn-npoeeney%2Csn-npoe7nz7&ms=au%2Crdu&mv=m&mvi=1&pl=62&initcwndbps=327500&vprv=1&mime=audio%2Fmp4&gir=yes&clen=2223860&dur=137.369&lmt=1638076977438400&mt=1658260164&fvip=5&keepalive=yes&fexp=24001373%2C24007246&c=ANDROID&txp=6311224&sparams=expire%2Cei%2Cip%2Cid%2Citag%2Csource%2Crequiressl%2Cvprv%2Cmime%2Cgir%2Cclen%2Cdur%2Clmt&sig=AOq0QJ8wRQIgdsLUEaA89R-ZKa0lemYg1h17ID7Kaibvhrdz-Qs6MesCIQDrF06lNaIP__UjrRBgR_6NhZ4HItipzJt_RJ5by0i3Mg%3D%3D&lsparams=mh%2Cmm%2Cmn%2Cms%2Cmv%2Cmvi%2Cpl%2Cinitcwndbps&lsig=AG3C_xAwRQIhAMkoUZjnSdxpJTiW9eM1ymLyQUoJq5t-EQGG3FCqKL-AAiB7PmkktX6Px-fhcgidlMnowNIvOtV9tgaAmZnSCr2zog%3D%3D", "language": "", "language_preference": -1, "ext": "m4a", "vcodec": "none", "acodec": "mp4a.40.2", "abr": 129.511, "downloader_options": {"http_chunk_size": 10485760}, "container": "m4a_dash", "protocol": "https", "audio_ext": "m4a", "video_ext": "none", "format": "140 - audio only (medium)", "resolution": "audio only", "http_headers": {"User-Agent": "Mozilla/5.0 (Windows NT 10.0; Win64; x64) AppleWebKit/537.36 (KHTML, like Gecko) Chrome/70.0.3533.0 Safari/537.36", "Accept-Charset": "ISO-8859-1,utf-8;q=0.7,*;q=0.7", "Accept": "text/html,application/xhtml+xml,application/xml;q=0.9,*/*;q=0.8", "Accept-Encoding": "gzip, deflate", "Accept-Language": "en-us,en;q=0.5"}}, {"asr": 48000, "filesize": 1920839, "format_id": "251", "format_note": "medium", "source_preference": -1, "quality": 3, "tbr": 111.887, "url": "https://rr1---sn-npoeeney.googlevideo.com/videoplayback?expire=1658282174&ei=XgzXYu6tJ42YvwSvr5u4Dg&ip=2400%3A6180%3A0%3Ad0%3A%3Ad34%3Af001&id=o-AIzsJMYjBr9VLOtvgvW4TdPQKyvORN71gpt6S31ZPFHJ&itag=251&source=youtube&requiressl=yes&mh=6v&mm=31%2C29&mn=sn-npoeeney%2Csn-npoe7nz7&ms=au%2Crdu&mv=m&mvi=1&pl=62&initcwndbps=327500&vprv=1&mime=audio%2Fwebm&gir=yes&clen=1920839&dur=137.341&lmt=1638076986449022&mt=1658260164&fvip=5&keepalive=yes&fexp=24001373%2C24007246&c=ANDROID&txp=6311224&sparams=expire%2Cei%2Cip%2Cid%2Citag%2Csource%2Crequiressl%2Cvprv%2Cmime%2Cgir%2Cclen%2Cdur%2Clmt&sig=AOq0QJ8wRAIgRh3HD7AmjcGNz07wEXdSb_KCzFuATUJheF9uRYcSiNwCIHIzEkSo5VPlOqC1gdxmbldtCZyni3dxaSv7WtbNbq4M&lsparams=mh%2Cmm%2Cmn%2Cms%2Cmv%2Cmvi%2Cpl%2Cinitcwndbps&lsig=AG3C_xAwRQIhAMkoUZjnSdxpJTiW9eM1ymLyQUoJq5t-EQGG3FCqKL-AAiB7PmkktX6Px-fhcgidlMnowNIvOtV9tgaAmZnSCr2zog%3D%3D", "language": "", "language_preference": -1, "ext": "webm", "vcodec": "none", "acodec": "opus", "abr": 111.887, "downloader_options": {"http_chunk_size": 10485760}, "container": "webm_dash", "protocol": "https", "audio_ext": "webm", "video_ext": "none", "format": "251 - audio only (medium)", "resolution": "audio only", "http_headers": {"User-Agent": "Mozilla/5.0 (Windows NT 10.0; Win64; x64) AppleWebKit/537.36 (KHTML, like Gecko) Chrome/70.0.3533.0 Safari/537.36", "Accept-Charset": "ISO-8859-1,utf-8;q=0.7,*;q=0.7", "Accept": "text/html,application/xhtml+xml,application/xml;q=0.9,*/*;q=0.8", "Accept-Encoding": "gzip, deflate", "Accept-Language": "en-us,en;q=0.5"}}, {"asr": 22050, "filesize": 1349199, "format_id": "17", "format_note": "144p", "source_preference": -1, "fps": 7, "height": 144, "quality": 0, "tbr": 78.547, "url": "https://rr1---sn-npoeeney.googlevideo.com/videoplayback?expire=1658282174&ei=XgzXYu6tJ42YvwSvr5u4Dg&ip=2400%3A6180%3A0%3Ad0%3A%3Ad34%3Af001&id=o-AIzsJMYjBr9VLOtvgvW4TdPQKyvORN71gpt6S31ZPFHJ&itag=17&source=youtube&requiressl=yes&mh=6v&mm=31%2C29&mn=sn-npoeeney%2Csn-npoe7nz7&ms=au%2Crdu&mv=m&mvi=1&pl=62&initcwndbps=327500&vprv=1&mime=video%2F3gpp&gir=yes&clen=1349199&dur=137.415&lmt=1638076980938506&mt=1658260164&fvip=5&fexp=24001373%2C24007246&c=ANDROID&txp=6311224&sparams=expire%2Cei%2Cip%2Cid%2Citag%2Csource%2Crequiressl%2Cvprv%2Cmime%2Cgir%2Cclen%2Cdur%2Clmt&sig=AOq0QJ8wRAIgQM7WIKdnqE6TG7Jai-T5ut62yrXslwrXa0k1oypYllsCIFU2taCOuLYq7q1-F1MuFder2f4XBqXZYrPJ38nbrvOZ&lsparams=mh%2Cmm%2Cmn%2Cms%2Cmv%2Cmvi%2Cpl%2Cinitcwndbps&lsig=AG3C_xAwRQIhAMkoUZjnSdxpJTiW9eM1ymLyQUoJq5t-EQGG3FCqKL-AAiB7PmkktX6Px-fhcgidlMnowNIvOtV9tgaAmZnSCr2zog%3D%3D", "width": 176, "language": "", "language_preference": -1, "ext": "3gp", "vcodec": "mp4v.20.3", "acodec": "mp4a.40.2", "dynamic_range": "SDR", "protocol": "https", "video_ext": "3gp", "audio_ext": "none", "vbr": 78.547, "abr": 0.0, "format": "17 - 176x144 (144p)", "resolution": "176x144", "http_headers": {"User-Agent": "Mozilla/5.0 (Windows NT 10.0; Win64; x64) AppleWebKit/537.36 (KHTML, like Gecko) Chrome/70.0.3533.0 Safari/537.36", "Accept-Charset": "ISO-8859-1,utf-8;q=0.7,*;q=0.7", "Accept": "text/html,application/xhtml+xml,application/xml;q=0.9,*/*;q=0.8", "Accept-Encoding": "gzip, deflate", "Accept-Language": "en-us,en;q=0.5"}}, {"filesize": 1659189, "format_id": "160", "format_note": "144p", "source_preference": -1, "fps": 30, "height": 144, "quality": 0, "tbr": 96.673, "url": "https://rr1---sn-npoeeney.googlevideo.com/videoplayback?expire=1658282174&ei=XgzXYu6tJ42YvwSvr5u4Dg&ip=2400%3A6180%3A0%3Ad0%3A%3Ad34%3Af001&id=o-AIzsJMYjBr9VLOtvgvW4TdPQKyvORN71gpt6S31ZPFHJ&itag=160&source=youtube&requiressl=yes&mh=6v&mm=31%2C29&mn=sn-npoeeney%2Csn-npoe7nz7&ms=au%2Crdu&mv=m&mvi=1&pl=62&initcwndbps=327500&vprv=1&mime=video%2Fmp4&gir=yes&clen=1659189&dur=137.303&lmt=1638076978124362&mt=1658260164&fvip=5&keepalive=yes&fexp=24001373%2C24007246&c=ANDROID&txp=6316224&sparams=expire%2Cei%2Cip%2Cid%2Citag%2Csource%2Crequiressl%2Cvprv%2Cmime%2Cgir%2Cclen%2Cdur%2Clmt&sig=AOq0QJ8wRQIgE69SiQe92EFVzJysghXXuey3BfPNGv7SAvaK5Gc7PD0CIQDeKHSVd-GRyjSgk8OQVX-FWUlEPgj3rm1Yy_oxo2HB0A%3D%3D&lsparams=mh%2Cmm%2Cmn%2Cms%2Cmv%2Cmvi%2Cpl%2Cinitcwndbps&lsig=AG3C_xAwRQIhAMkoUZjnSdxpJTiW9eM1ymLyQUoJq5t-EQGG3FCqKL-AAiB7PmkktX6Px-fhcgidlMnowNIvOtV9tgaAmZnSCr2zog%3D%3D", "width": 256, "language": "", "language_preference": -1, "ext": "mp4", "vcodec": "avc1.4d400c", "acodec": "none", "dynamic_range": "SDR", "vbr": 96.673, "downloader_options": {"http_chunk_size": 10485760}, "container": "mp4_dash", "protocol": "https", "video_ext": "mp4", "audio_ext": "none", "format": "160 - 256x144 (144p)", "resolution": "256x144", "http_headers": {"User-Agent": "Mozilla/5.0 (Windows NT 10.0; Win64; x64) AppleWebKit/537.36 (KHTML, like Gecko) Chrome/70.0.3533.0 Safari/537.36", "Accept-Charset": "ISO-8859-1,utf-8;q=0.7,*;q=0.7", "Accept": "text/html,application/xhtml+xml,application/xml;q=0.9,*/*;q=0.8", "Accept-Encoding": "gzip, deflate", "Accept-Language": "en-us,en;q=0.5"}}, {"filesize": 1489954, "format_id": "278", "format_note": "144p", "source_preference": -1, "fps": 30, "height": 144, "quality": 0, "tbr": 86.812, "url": "https://rr1---sn-npoeeney.googlevideo.com/videoplayback?expire=1658282174&ei=XgzXYu6tJ42YvwSvr5u4Dg&ip=2400%3A6180%3A0%3Ad0%3A%3Ad34%3Af001&id=o-AIzsJMYjBr9VLOtvgvW4TdPQKyvORN71gpt6S31ZPFHJ&itag=278&source=youtube&requiressl=yes&mh=6v&mm=31%2C29&mn=sn-npoeeney%2Csn-npoe7nz7&ms=au%2Crdu&mv=m&mvi=1&pl=62&initcwndbps=327500&vprv=1&mime=video%2Fwebm&gir=yes&clen=1489954&dur=137.303&lmt=1638076977125069&mt=1658260164&fvip=5&keepalive=yes&fexp=24001373%2C24007246&c=ANDROID&txp=6316224&sparams=expire%2Cei%2Cip%2Cid%2Citag%2Csource%2Crequiressl%2Cvprv%2Cmime%2Cgir%2Cclen%2Cdur%2Clmt&sig=AOq0QJ8wRQIhAPx6P765iKhrKKl0F-OSItQiN0YJ8LNbaxfL9ACGt5kQAiA-tDhNK-Miz6tjGhm5djMcJQthL6TflELwwkEQ3-5Ncg%3D%3D&lsparams=mh%2Cmm%2Cmn%2Cms%2Cmv%2Cmvi%2Cpl%2Cinitcwndbps&lsig=AG3C_xAwRQIhAMkoUZjnSdxpJTiW9eM1ymLyQUoJq5t-EQGG3FCqKL-AAiB7PmkktX6Px-fhcgidlMnowNIvOtV9tgaAmZnSCr2zog%3D%3D", "width": 256, "language": "", "language_preference": -1, "ext": "webm", "vcodec": "vp9", "acodec": "none", "dynamic_range": "SDR", "vbr": 86.812, "downloader_options": {"http_chunk_size": 10485760}, "container": "webm_dash", "protocol": "https", "video_ext": "webm", "audio_ext": "none", "format": "278 - 256x144 (144p)", "resolution": "256x144", "http_headers": {"User-Agent": "Mozilla/5.0 (Windows NT 10.0; Win64; x64) AppleWebKit/537.36 (KHTML, like Gecko) Chrome/70.0.3533.0 Safari/537.36", "Accept-Charset": "ISO-8859-1,utf-8;q=0.7,*;q=0.7", "Accept": "text/html,application/xhtml+xml,application/xml;q=0.9,*/*;q=0.8", "Accept-Encoding": "gzip, deflate", "Accept-Language": "en-us,en;q=0.5"}}, {"filesize": 3526680, "format_id": "133", "format_note": "240p", "source_preference": -1, "fps": 30, "height": 240, "quality": 5, "tbr": 205.483, "url": "https://rr1---sn-npoeeney.googlevideo.com/videoplayback?expire=1658282174&ei=XgzXYu6tJ42YvwSvr5u4Dg&ip=2400%3A6180%3A0%3Ad0%3A%3Ad34%3Af001&id=o-AIzsJMYjBr9VLOtvgvW4TdPQKyvORN71gpt6S31ZPFHJ&itag=133&source=youtube&requiressl=yes&mh=6v&mm=31%2C29&mn=sn-npoeeney%2Csn-npoe7nz7&ms=au%2Crdu&mv=m&mvi=1&pl=62&initcwndbps=327500&vprv=1&mime=video%2Fmp4&gir=yes&clen=3526680&dur=137.303&lmt=1638076977994077&mt=1658260164&fvip=5&keepalive=yes&fexp=24001373%2C24007246&c=ANDROID&txp=6316224&sparams=expire%2Cei%2Cip%2Cid%2Citag%2Csource%2Crequiressl%2Cvprv%2Cmime%2Cgir%2Cclen%2Cdur%2Clmt&sig=AOq0QJ8wRAIgECZUzrMneujJ3LaIrpYCMbFGbAzSYURtZeJwM0z-hWICIExJgzZCRPY2oHUhrP2TTwItiBKO7C_b5cfqVrkC7OO6&lsparams=mh%2Cmm%2Cmn%2Cms%2Cmv%2Cmvi%2Cpl%2Cinitcwndbps&lsig=AG3C_xAwRQIhAMkoUZjnSdxpJTiW9eM1ymLyQUoJq5t-EQGG3FCqKL-AAiB7PmkktX6Px-fhcgidlMnowNIvOtV9tgaAmZnSCr2zog%3D%3D", "width": 426, "language": "", "language_preference": -1, "ext": "mp4", "vcodec": "avc1.4d4015", "acodec": "none", "dynamic_range": "SDR", "vbr": 205.483, "downloader_options": {"http_chunk_size": 10485760}, "container": "mp4_dash", "protocol": "https", "video_ext": "mp4", "audio_ext": "none", "format": "133 - 426x240 (240p)", "resolution": "426x240", "http_headers": {"User-Agent": "Mozilla/5.0 (Windows NT 10.0; Win64; x64) AppleWebKit/537.36 (KHTML, like Gecko) Chrome/70.0.3533.0 Safari/537.36", "Accept-Charset": "ISO-8859-1,utf-8;q=0.7,*;q=0.7", "Accept": "text/html,application/xhtml+xml,application/xml;q=0.9,*/*;q=0.8", "Accept-Encoding": "gzip, deflate", "Accept-Language": "en-us,en;q=0.5"}}, {"filesize": 2768712, "format_id": "242", "format_note": "240p", "source_preference": -1, "fps": 30, "height": 240, "quality": 5, "tbr": 161.319, "url": "https://rr1---sn-npoeeney.googlevideo.com/videoplayback?expire=1658282174&ei=XgzXYu6tJ42YvwSvr5u4Dg&ip=2400%3A6180%3A0%3Ad0%3A%3Ad34%3Af001&id=o-AIzsJMYjBr9VLOtvgvW4TdPQKyvORN71gpt6S31ZPFHJ&itag=242&source=youtube&requiressl=yes&mh=6v&mm=31%2C29&mn=sn-npoeeney%2Csn-npoe7nz7&ms=au%2Crdu&mv=m&mvi=1&pl=62&initcwndbps=327500&vprv=1&mime=video%2Fwebm&gir=yes&clen=2768712&dur=137.303&lmt=1638076977269678&mt=1658260164&fvip=5&keepalive=yes&fexp=24001373%2C24007246&c=ANDROID&txp=6316224&sparams=expire%2Cei%2Cip%2Cid%2Citag%2Csource%2Crequiressl%2Cvprv%2Cmime%2Cgir%2Cclen%2Cdur%2Clmt&sig=AOq0QJ8wRgIhAPQ7d1jKqPN53Ddj-uVExPrYYLG-H3DpV1MGRRIof5p0AiEA3Ue0tx7JVXOliFj_zJN1fLdA0B7fXZKDkm8kvaga5PU%3D&lsparams=mh%2Cmm%2Cmn%2Cms%2Cmv%2Cmvi%2Cpl%2Cinitcwndbps&lsig=AG3C_xAwRQIhAMkoUZjnSdxpJTiW9eM1ymLyQUoJq5t-EQGG3FCqKL-AAiB7PmkktX6Px-fhcgidlMnowNIvOtV9tgaAmZnSCr2zog%3D%3D", "width": 426, "language": "", "language_preference": -1, "ext": "webm", "vcodec": "vp9", "acodec": "none", "dynamic_range": "SDR", "vbr": 161.319, "downloader_options": {"http_chunk_size": 10485760}, "container": "webm_dash", "protocol": "https", "video_ext": "webm", "audio_ext": "none", "format": "242 - 426x240 (240p)", "resolution": "426x240", "http_headers": {"User-Agent": "Mozilla/5.0 (Windows NT 10.0; Win64; x64) AppleWebKit/537.36 (KHTML, like Gecko) Chrome/70.0.3533.0 Safari/537.36", "Accept-Charset": "ISO-8859-1,utf-8;q=0.7,*;q=0.7", "Accept": "text/html,application/xhtml+xml,application/xml;q=0.9,*/*;q=0.8", "Accept-Encoding": "gzip, deflate", "Accept-Language": "en-us,en;q=0.5"}}, {"filesize": 6741606, "format_id": "134", "format_note": "360p", "source_preference": -1, "fps": 30, "height": 360, "quality": 6, "tbr": 392.801, "url": "https://rr1---sn-npoeeney.googlevideo.com/videoplayback?expire=1658282174&ei=XgzXYu6tJ42YvwSvr5u4Dg&ip=2400%3A6180%3A0%3Ad0%3A%3Ad34%3Af001&id=o-AIzsJMYjBr9VLOtvgvW4TdPQKyvORN71gpt6S31ZPFHJ&itag=134&source=youtube&requiressl=yes&mh=6v&mm=31%2C29&mn=sn-npoeeney%2Csn-npoe7nz7&ms=au%2Crdu&mv=m&mvi=1&pl=62&initcwndbps=327500&vprv=1&mime=video%2Fmp4&gir=yes&clen=6741606&dur=137.303&lmt=1638076978130678&mt=1658260164&fvip=5&keepalive=yes&fexp=24001373%2C24007246&c=ANDROID&txp=6316224&sparams=expire%2Cei%2Cip%2Cid%2Citag%2Csource%2Crequiressl%2Cvprv%2Cmime%2Cgir%2Cclen%2Cdur%2Clmt&sig=AOq0QJ8wRAIgIIgBlXZ0LWxJSd0llDUQsxJJWitUpi3jCNRbeGIlmcACIFmpgTvX1xLB_3aiMHcvueTI75OvgG4pZzluCiJPCpZk&lsparams=mh%2Cmm%2Cmn%2Cms%2Cmv%2Cmvi%2Cpl%2Cinitcwndbps&lsig=AG3C_xAwRQIhAMkoUZjnSdxpJTiW9eM1ymLyQUoJq5t-EQGG3FCqKL-AAiB7PmkktX6Px-fhcgidlMnowNIvOtV9tgaAmZnSCr2zog%3D%3D", "width": 640, "language": "", "language_preference": -1, "ext": "mp4", "vcodec": "avc1.4d401e", "acodec": "none", "dynamic_range": "SDR", "vbr": 392.801, "downloader_options": {"http_chunk_size": 10485760}, "container": "mp4_dash", "protocol": "https", "video_ext": "mp4", "audio_ext": "none", "format": "134 - 640x360 (360p)", "resolution": "640x360", "http_headers": {"User-Agent": "Mozilla/5.0 (Windows NT 10.0; Win64; x64) AppleWebKit/537.36 (KHTML, like Gecko) Chrome/70.0.3533.0 Safari/537.36", "Accept-Charset": "ISO-8859-1,utf-8;q=0.7,*;q=0.7", "Accept": "text/html,application/xhtml+xml,application/xml;q=0.9,*/*;q=0.8", "Accept-Encoding": "gzip, deflate", "Accept-Language": "en-us,en;q=0.5"}}, {"asr": 44100, "filesize": 8402544, "format_id": "18", "format_note": "360p", "source_preference": -1, "fps": 30, "height": 360, "quality": 6, "tbr": 489.341, "url": "https://rr1---sn-npoeeney.googlevideo.com/videoplayback?expire=1658282174&ei=XgzXYu6tJ42YvwSvr5u4Dg&ip=2400%3A6180%3A0%3Ad0%3A%3Ad34%3Af001&id=o-AIzsJMYjBr9VLOtvgvW4TdPQKyvORN71gpt6S31ZPFHJ&itag=18&source=youtube&requiressl=yes&mh=6v&mm=31%2C29&mn=sn-npoeeney%2Csn-npoe7nz7&ms=au%2Crdu&mv=m&mvi=1&pl=62&initcwndbps=327500&vprv=1&mime=video%2Fmp4&gir=yes&clen=8402544&ratebypass=yes&dur=137.369&lmt=1638076978467696&mt=1658260164&fvip=5&fexp=24001373%2C24007246&c=ANDROID&txp=6319224&sparams=expire%2Cei%2Cip%2Cid%2Citag%2Csource%2Crequiressl%2Cvprv%2Cmime%2Cgir%2Cclen%2Cratebypass%2Cdur%2Clmt&sig=AOq0QJ8wRgIhAMBSDxjXEMh_YyYwO7Pnr43wbsdYjzs9hHFzNj7UZJ33AiEA3EML6i7YY29Bo4NgqRp3haqsx0qBA6OVttl5Log5cfw%3D&lsparams=mh%2Cmm%2Cmn%2Cms%2Cmv%2Cmvi%2Cpl%2Cinitcwndbps&lsig=AG3C_xAwRQIhAMkoUZjnSdxpJTiW9eM1ymLyQUoJq5t-EQGG3FCqKL-AAiB7PmkktX6Px-fhcgidlMnowNIvOtV9tgaAmZnSCr2zog%3D%3D", "width": 640, "language": "", "language_preference": -1, "ext": "mp4", "vcodec": "avc1.42001E", "acodec": "mp4a.40.2", "dynamic_range": "SDR", "protocol": "https", "video_ext": "mp4", "audio_ext": "none", "vbr": 489.341, "abr": 0.0, "format": "18 - 640x360 (360p)", "resolution": "640x360", "http_headers": {"User-Agent": "Mozilla/5.0 (Windows NT 10.0; Win64; x64) AppleWebKit/537.36 (KHTML, like Gecko) Chrome/70.0.3533.0 Safari/537.36", "Accept-Charset": "ISO-8859-1,utf-8;q=0.7,*;q=0.7", "Accept": "text/html,application/xhtml+xml,application/xml;q=0.9,*/*;q=0.8", "Accept-Encoding": "gzip, deflate", "Accept-Language": "en-us,en;q=0.5"}}, {"filesize": 4530533, "format_id": "243", "format_note": "360p", "source_preference": -1, "fps": 30, "height": 360, "quality": 6, "tbr": 263.972, "url": "https://rr1---sn-npoeeney.googlevideo.com/videoplayback?expire=1658282174&ei=XgzXYu6tJ42YvwSvr5u4Dg&ip=2400%3A6180%3A0%3Ad0%3A%3Ad34%3Af001&id=o-AIzsJMYjBr9VLOtvgvW4TdPQKyvORN71gpt6S31ZPFHJ&itag=243&source=youtube&requiressl=yes&mh=6v&mm=31%2C29&mn=sn-npoeeney%2Csn-npoe7nz7&ms=au%2Crdu&mv=m&mvi=1&pl=62&initcwndbps=327500&vprv=1&mime=video%2Fwebm&gir=yes&clen=4530533&dur=137.303&lmt=1638076977378521&mt=1658260164&fvip=5&keepalive=yes&fexp=24001373%2C24007246&c=ANDROID&txp=6316224&sparams=expire%2Cei%2Cip%2Cid%2Citag%2Csource%2Crequiressl%2Cvprv%2Cmime%2Cgir%2Cclen%2Cdur%2Clmt&sig=AOq0QJ8wRgIhAMuCdFtgScL2hszrFU3-NUME_NKjIbyMp8Us_Wc0SEdEAiEA1DQyfCTR8hVk0M9JvWbdAVQk0LYxKBa3gb1OQ9bkE34%3D&lsparams=mh%2Cmm%2Cmn%2Cms%2Cmv%2Cmvi%2Cpl%2Cinitcwndbps&lsig=AG3C_xAwRQIhAMkoUZjnSdxpJTiW9eM1ymLyQUoJq5t-EQGG3FCqKL-AAiB7PmkktX6Px-fhcgidlMnowNIvOtV9tgaAmZnSCr2zog%3D%3D", "width": 640, "language": "", "language_preference": -1, "ext": "webm", "vcodec": "vp9", "acodec": "none", "dynamic_range": "SDR", "vbr": 263.972, "downloader_options": {"http_chunk_size": 10485760}, "container": "webm_dash", "protocol": "https", "video_ext": "webm", "audio_ext": "none", "format": "243 - 640x360 (360p)", "resolution": "640x360", "http_headers": {"User-Agent": "Mozilla/5.0 (Windows NT 10.0; Win64; x64) AppleWebKit/537.36 (KHTML, like Gecko) Chrome/70.0.3533.0 Safari/537.36", "Accept-Charset": "ISO-8859-1,utf-8;q=0.7,*;q=0.7", "Accept": "text/html,application/xhtml+xml,application/xml;q=0.9,*/*;q=0.8", "Accept-Encoding": "gzip, deflate", "Accept-Language": "en-us,en;q=0.5"}}, {"filesize": 11765258, "format_id": "135", "format_note": "480p", "source_preference": -1, "fps": 30, "height": 480, "quality": 7, "tbr": 685.506, "url": "https://rr1---sn-npoeeney.googlevideo.com/videoplayback?expire=1658282174&ei=XgzXYu6tJ42YvwSvr5u4Dg&ip=2400%3A6180%3A0%3Ad0%3A%3Ad34%3Af001&id=o-AIzsJMYjBr9VLOtvgvW4TdPQKyvORN71gpt6S31ZPFHJ&itag=135&source=youtube&requiressl=yes&mh=6v&mm=31%2C29&mn=sn-npoeeney%2Csn-npoe7nz7&ms=au%2Crdu&mv=m&mvi=1&pl=62&initcwndbps=327500&vprv=1&mime=video%2Fmp4&gir=yes&clen=11765258&dur=137.303&lmt=1638076979244208&mt=1658260164&fvip=5&keepalive=yes&fexp=24001373%2C24007246&c=ANDROID&txp=6316224&sparams=expire%2Cei%2Cip%2Cid%2Citag%2Csource%2Crequiressl%2Cvprv%2Cmime%2Cgir%2Cclen%2Cdur%2Clmt&sig=AOq0QJ8wRQIgXJEwH6uMpPKqL78S6_VX9vs0INv78V-OAercDxWZQrcCIQDUKbnw0yVKK2E223JA1sJhhrOV2dJf98cMlXS_wa0XnQ%3D%3D&lsparams=mh%2Cmm%2Cmn%2Cms%2Cmv%2Cmvi%2Cpl%2Cinitcwndbps&lsig=AG3C_xAwRQIhAMkoUZjnSdxpJTiW9eM1ymLyQUoJq5t-EQGG3FCqKL-AAiB7PmkktX6Px-fhcgidlMnowNIvOtV9tgaAmZnSCr2zog%3D%3D", "width": 854, "language": "", "language_preference": -1, "ext": "mp4", "vcodec": "avc1.4d401f", "acodec": "none", "dynamic_range": "SDR", "vbr": 685.506, "downloader_options": {"http_chunk_size": 10485760}, "container": "mp4_dash", "protocol": "https", "video_ext": "mp4", "audio_ext": "none", "format": "135 - 854x480 (480p)", "resolution": "854x480", "http_headers": {"User-Agent": "Mozilla/5.0 (Windows NT 10.0; Win64; x64) AppleWebKit/537.36 (KHTML, like Gecko) Chrome/70.0.3533.0 Safari/537.36", "Accept-Charset": "ISO-8859-1,utf-8;q=0.7,*;q=0.7", "Accept": "text/html,application/xhtml+xml,application/xml;q=0.9,*/*;q=0.8", "Accept-Encoding": "gzip, deflate", "Accept-Language": "en-us,en;q=0.5"}}, {"filesize": 7471483, "format_id": "244", "format_note": "480p", "source_preference": -1, "fps": 30, "height": 480, "quality": 7, "tbr": 435.328, "url": "https://rr1---sn-npoeeney.googlevideo.com/videoplayback?expire=1658282174&ei=XgzXYu6tJ42YvwSvr5u4Dg&ip=2400%3A6180%3A0%3Ad0%3A%3Ad34%3Af001&id=o-AIzsJMYjBr9VLOtvgvW4TdPQKyvORN71gpt6S31ZPFHJ&itag=244&source=youtube&requiressl=yes&mh=6v&mm=31%2C29&mn=sn-npoeeney%2Csn-npoe7nz7&ms=au%2Crdu&mv=m&mvi=1&pl=62&initcwndbps=327500&vprv=1&mime=video%2Fwebm&gir=yes&clen=7471483&dur=137.303&lmt=1638076978022773&mt=1658260164&fvip=5&keepalive=yes&fexp=24001373%2C24007246&c=ANDROID&txp=6316224&sparams=expire%2Cei%2Cip%2Cid%2Citag%2Csource%2Crequiressl%2Cvprv%2Cmime%2Cgir%2Cclen%2Cdur%2Clmt&sig=AOq0QJ8wRQIhAKXekDpx41SKwjowk0y0SkuLab8xeZWbJtjwM__dt1lRAiBJOl_22xhpt2CVVKfRQBREuRgQwWchbYH0oos9V_-IKQ%3D%3D&lsparams=mh%2Cmm%2Cmn%2Cms%2Cmv%2Cmvi%2Cpl%2Cinitcwndbps&lsig=AG3C_xAwRQIhAMkoUZjnSdxpJTiW9eM1ymLyQUoJq5t-EQGG3FCqKL-AAiB7PmkktX6Px-fhcgidlMnowNIvOtV9tgaAmZnSCr2zog%3D%3D", "width": 854, "language": "", "language_preference": -1, "ext": "webm", "vcodec": "vp9", "acodec": "none", "dynamic_range": "SDR", "vbr": 435.328, "downloader_options": {"http_chunk_size": 10485760}, "container": "webm_dash", "protocol": "https", "video_ext": "webm", "audio_ext": "none", "format": "244 - 854x480 (480p)", "resolution": "854x480", "http_headers": {"User-Agent": "Mozilla/5.0 (Windows NT 10.0; Win64; x64) AppleWebKit/537.36 (KHTML, like Gecko) Chrome/70.0.3533.0 Safari/537.36", "Accept-Charset": "ISO-8859-1,utf-8;q=0.7,*;q=0.7", "Accept": "text/html,application/xhtml+xml,application/xml;q=0.9,*/*;q=0.8", "Accept-Encoding": "gzip, deflate", "Accept-Language": "en-us,en;q=0.5"}}, {"filesize": 21015973, "format_id": "136", "format_note": "720p", "source_preference": -1, "fps": 30, "height": 720, "quality": 8, "tbr": 1224.501, "url": "https://rr1---sn-npoeeney.googlevideo.com/videoplayback?expire=1658282174&ei=XgzXYu6tJ42YvwSvr5u4Dg&ip=2400%3A6180%3A0%3Ad0%3A%3Ad34%3Af001&id=o-AIzsJMYjBr9VLOtvgvW4TdPQKyvORN71gpt6S31ZPFHJ&itag=136&source=youtube&requiressl=yes&mh=6v&mm=31%2C29&mn=sn-npoeeney%2Csn-npoe7nz7&ms=au%2Crdu&mv=m&mvi=1&pl=62&initcwndbps=327500&vprv=1&mime=video%2Fmp4&gir=yes&clen=21015973&dur=137.303&lmt=1638076978988495&mt=1658260164&fvip=5&keepalive=yes&fexp=24001373%2C24007246&c=ANDROID&txp=6316224&sparams=expire%2Cei%2Cip%2Cid%2Citag%2Csource%2Crequiressl%2Cvprv%2Cmime%2Cgir%2Cclen%2Cdur%2Clmt&sig=AOq0QJ8wRAIgBXwYgrLWXQJqWd03Z6pXRjy2UbUa9SRs-9RcFYrV2lYCIDwi5fH-xiongaAEfROnDPWXufqSz4l8JZQQh5VsXgc8&lsparams=mh%2Cmm%2Cmn%2Cms%2Cmv%2Cmvi%2Cpl%2Cinitcwndbps&lsig=AG3C_xAwRQIhAMkoUZjnSdxpJTiW9eM1ymLyQUoJq5t-EQGG3FCqKL-AAiB7PmkktX6Px-fhcgidlMnowNIvOtV9tgaAmZnSCr2zog%3D%3D", "width": 1280, "language": "", "language_preference": -1, "ext": "mp4", "vcodec": "avc1.64001f", "acodec": "none", "dynamic_range": "SDR", "vbr": 1224.501, "downloader_options": {"http_chunk_size": 10485760}, "container": "mp4_dash", "protocol": "https", "video_ext": "mp4", "audio_ext": "none", "format": "136 - 1280x720 (720p)", "resolution": "1280x720", "http_headers": {"User-Agent": "Mozilla/5.0 (Windows NT 10.0; Win64; x64) AppleWebKit/537.36 (KHTML, like Gecko) Chrome/70.0.3533.0 Safari/537.36", "Accept-Charset": "ISO-8859-1,utf-8;q=0.7,*;q=0.7", "Accept": "text/html,application/xhtml+xml,application/xml;q=0.9,*/*;q=0.8", "Accept-Encoding": "gzip, deflate", "Accept-Language": "en-us,en;q=0.5"}}, {"asr": 44100, "format_id": "22", "format_note": "720p", "source_preference": -1, "fps": 30, "height": 720, "quality": 8, "tbr": 1352.826, "url": "https://rr1---sn-npoeeney.googlevideo.com/videoplayback?expire=1658282174&ei=XgzXYu6tJ42YvwSvr5u4Dg&ip=2400%3A6180%3A0%3Ad0%3A%3Ad34%3Af001&id=o-AIzsJMYjBr9VLOtvgvW4TdPQKyvORN71gpt6S31ZPFHJ&itag=22&source=youtube&requiressl=yes&mh=6v&mm=31%2C29&mn=sn-npoeeney%2Csn-npoe7nz7&ms=au%2Crdu&mv=m&mvi=1&pl=62&initcwndbps=327500&vprv=1&mime=video%2Fmp4&cnr=14&ratebypass=yes&dur=137.369&lmt=1638076981314019&mt=1658260164&fvip=5&fexp=24001373%2C24007246&c=ANDROID&txp=6311224&sparams=expire%2Cei%2Cip%2Cid%2Citag%2Csource%2Crequiressl%2Cvprv%2Cmime%2Ccnr%2Cratebypass%2Cdur%2Clmt&sig=AOq0QJ8wRAIgMWQ1SwZWlXvcvIwcGYr_FWIpKpPuEYAU3Lt2BLVTYkUCIAi7-Vu4-K-4K7GFdwv5lWlesgBmTNNG6k931dKJF29S&lsparams=mh%2Cmm%2Cmn%2Cms%2Cmv%2Cmvi%2Cpl%2Cinitcwndbps&lsig=AG3C_xAwRQIhAMkoUZjnSdxpJTiW9eM1ymLyQUoJq5t-EQGG3FCqKL-AAiB7PmkktX6Px-fhcgidlMnowNIvOtV9tgaAmZnSCr2zog%3D%3D", "width": 1280, "language": "", "language_preference": -1, "ext": "mp4", "vcodec": "avc1.64001F", "acodec": "mp4a.40.2", "dynamic_range": "SDR", "protocol": "https", "video_ext": "mp4", "audio_ext": "none", "vbr": 1352.826, "abr": 0.0, "format": "22 - 1280x720 (720p)", "resolution": "1280x720", "filesize_approx": 23723156.736, "http_headers": {"User-Agent": "Mozilla/5.0 (Windows NT 10.0; Win64; x64) AppleWebKit/537.36 (KHTML, like Gecko) Chrome/70.0.3533.0 Safari/537.36", "Accept-Charset": "ISO-8859-1,utf-8;q=0.7,*;q=0.7", "Accept": "text/html,application/xhtml+xml,application/xml;q=0.9,*/*;q=0.8", "Accept-Encoding": "gzip, deflate", "Accept-Language": "en-us,en;q=0.5"}}, {"filesize": 13775422, "format_id": "247", "format_note": "720p", "source_preference": -1, "fps": 30, "height": 720, "quality": 8, "tbr": 802.629, "url": "https://rr1---sn-npoeeney.googlevideo.com/videoplayback?expire=1658282174&ei=XgzXYu6tJ42YvwSvr5u4Dg&ip=2400%3A6180%3A0%3Ad0%3A%3Ad34%3Af001&id=o-AIzsJMYjBr9VLOtvgvW4TdPQKyvORN71gpt6S31ZPFHJ&itag=247&source=youtube&requiressl=yes&mh=6v&mm=31%2C29&mn=sn-npoeeney%2Csn-npoe7nz7&ms=au%2Crdu&mv=m&mvi=1&pl=62&initcwndbps=327500&vprv=1&mime=video%2Fwebm&gir=yes&clen=13775422&dur=137.303&lmt=1638076977336974&mt=1658260164&fvip=5&keepalive=yes&fexp=24001373%2C24007246&c=ANDROID&txp=6316224&sparams=expire%2Cei%2Cip%2Cid%2Citag%2Csource%2Crequiressl%2Cvprv%2Cmime%2Cgir%2Cclen%2Cdur%2Clmt&sig=AOq0QJ8wRQIhALNFfrUXza-kTktYguN5Gpx189hUCOVsV25Fo6-8mz6nAiAzL7wuOGhjbvk3RLIe9UQEJSG0H_LHjvZbAd6YyBoQcg%3D%3D&lsparams=mh%2Cmm%2Cmn%2Cms%2Cmv%2Cmvi%2Cpl%2Cinitcwndbps&lsig=AG3C_xAwRQIhAMkoUZjnSdxpJTiW9eM1ymLyQUoJq5t-EQGG3FCqKL-AAiB7PmkktX6Px-fhcgidlMnowNIvOtV9tgaAmZnSCr2zog%3D%3D", "width": 1280, "language": "", "language_preference": -1, "ext": "webm", "vcodec": "vp9", "acodec": "none", "dynamic_range": "SDR", "vbr": 802.629, "downloader_options": {"http_chunk_size": 10485760}, "container": "webm_dash", "protocol": "https", "video_ext": "webm", "audio_ext": "none", "format": "247 - 1280x720 (720p)", "resolution": "1280x720", "http_headers": {"User-Agent": "Mozilla/5.0 (Windows NT 10.0; Win64; x64) AppleWebKit/537.36 (KHTML, like Gecko) Chrome/70.0.3533.0 Safari/537.36", "Accept-Charset": "ISO-8859-1,utf-8;q=0.7,*;q=0.7", "Accept": "text/html,application/xhtml+xml,application/xml;q=0.9,*/*;q=0.8", "Accept-Encoding": "gzip, deflate", "Accept-Language": "en-us,en;q=0.5"}}], "thumbnails": [{"url": "https://i.ytimg.com/vi/a4jZzlWofAY/3.jpg", "preference": -37, "id": "0"}, {"url": "https://i.ytimg.com/vi_webp/a4jZzlWofAY/3.webp", "preference": -36, "id": "1"}, {"url": "https://i.ytimg.com/vi/a4jZzlWofAY/2.jpg", "preference": -35, "id": "2"}, {"url": "https://i.ytimg.com/vi_webp/a4jZzlWofAY/2.webp", "preference": -34, "id": "3"}, {"url": "https://i.ytimg.com/vi/a4jZzlWofAY/1.jpg", "preference": -33, "id": "4"}, {"url": "https://i.ytimg.com/vi_webp/a4jZzlWofAY/1.webp", "preference": -32, "id": "5"}, {"url": "https://i.ytimg.com/vi/a4jZzlWofAY/default.jpg", "preference": -31, "id": "6"}, {"url": "https://i.ytimg.com/vi_webp/a4jZzlWofAY/default.webp", "height": 90, "width": 120, "preference": -30, "id": "7", "resolution": "120x90"}, {"url": "https://i.ytimg.com/vi/a4jZzlWofAY/mq3.jpg", "preference": -29, "id": "8"}, {"url": "https://i.ytimg.com/vi_webp/a4jZzlWofAY/mq3.webp", "preference": -28, "id": "9"}, {"url": "https://i.ytimg.com/vi/a4jZzlWofAY/mq2.jpg", "preference": -27, "id": "10"}, {"url": "https://i.ytimg.com/vi_webp/a4jZzlWofAY/mq2.webp", "preference": -26, "id": "11"}, {"url": "https://i.ytimg.com/vi/a4jZzlWofAY/mq1.jpg", "preference": -25, "id": "12"}, {"url": "https://i.ytimg.com/vi_webp/a4jZzlWofAY/mq1.webp", "preference": -24, "id": "13"}, {"url": "https://i.ytimg.com/vi/a4jZzlWofAY/mqdefault.jpg", "preference": -23, "id": "14"}, {"url": "https://i.ytimg.com/vi_webp/a4jZzlWofAY/mqdefault.webp", "height": 180, "width": 320, "preference": -22, "id": "15", "resolution": "320x180"}, {"url": "https://i.ytimg.com/vi/a4jZzlWofAY/0.jpg", "preference": -21, "id": "16"}, {"url": "https://i.ytimg.com/vi_webp/a4jZzlWofAY/0.webp", "preference": -20, "id": "17"}, {"url": "https://i.ytimg.com/vi/a4jZzlWofAY/hq3.jpg", "preference": -19, "id": "18"}, {"url": "https://i.ytimg.com/vi_webp/a4jZzlWofAY/hq3.webp", "preference": -18, "id": "19"}, {"url": "https://i.ytimg.com/vi/a4jZzlWofAY/hq2.jpg", "preference": -17, "id": "20"}, {"url": "https://i.ytimg.com/vi_webp/a4jZzlWofAY/hq2.webp", "preference": -16, "id": "21"}, {"url": "https://i.ytimg.com/vi/a4jZzlWofAY/hq1.jpg", "preference": -15, "id": "22"}, {"url": "https://i.ytimg.com/vi_webp/a4jZzlWofAY/hq1.webp", "preference": -14, "id": "23"}, {"url": "https://i.ytimg.com/vi/a4jZzlWofAY/hqdefault.jpg", "preference": -13, "id": "24"}, {"url": "https://i.ytimg.com/vi/a4jZzlWofAY/hqdefault.jpg?sqp=-oaymwEbCKgBEF5IVfKriqkDDggBFQAAiEIYAXABwAEG&rs=AOn4CLC1nYIwYX7klMrboTdE0_GTpz4R8A", "height": 94, "width": 168, "preference": -13, "id": "25", "resolution": "168x94"}, {"url": "https://i.ytimg.com/vi/a4jZzlWofAY/hqdefault.jpg?sqp=-oaymwEbCMQBEG5IVfKriqkDDggBFQAAiEIYAXABwAEG&rs=AOn4CLBv2QfcahO1AdMcbMJ6KMMvY7dcNg", "height": 110, "width": 196, "preference": -13, "id": "26", "resolution": "196x110"}, {"url": "https://i.ytimg.com/vi/a4jZzlWofAY/hqdefault.jpg?sqp=-oaymwEcCPYBEIoBSFXyq4qpAw4IARUAAIhCGAFwAcABBg==&rs=AOn4CLBa4wfKf1QC7RRUmA6L11RZ8Zy65g", "height": 138, "width": 246, "preference": -13, "id": "27", "resolution": "246x138"}, {"url": "https://i.ytimg.com/vi/a4jZzlWofAY/hqdefault.jpg?sqp=-oaymwEcCNACELwBSFXyq4qpAw4IARUAAIhCGAFwAcABBg==&rs=AOn4CLDTydNyZvwjYQYa0wshcOc0I9oAxg", "height": 188, "width": 336, "preference": -13, "id": "28", "resolution": "336x188"}, {"url": "https://i.ytimg.com/vi_webp/a4jZzlWofAY/hqdefault.webp", "height": 360, "width": 480, "preference": -12, "id": "29", "resolution": "480x360"}, {"url": "https://i.ytimg.com/vi/a4jZzlWofAY/sd3.jpg", "preference": -11, "id": "30"}, {"url": "https://i.ytimg.com/vi_webp/a4jZzlWofAY/sd3.webp", "preference": -10, "id": "31"}, {"url": "https://i.ytimg.com/vi/a4jZzlWofAY/sd2.jpg", "preference": -9, "id": "32"}, {"url": "https://i.ytimg.com/vi_webp/a4jZzlWofAY/sd2.webp", "preference": -8, "id": "33"}, {"url": "https://i.ytimg.com/vi/a4jZzlWofAY/sd1.jpg", "preference": -7, "id": "34"}, {"url": "https://i.ytimg.com/vi_webp/a4jZzlWofAY/sd1.webp", "preference": -6, "id": "35"}, {"url": "https://i.ytimg.com/vi/a4jZzlWofAY/sddefault.jpg", "preference": -5, "id": "36"}, {"url": "https://i.ytimg.com/vi_webp/a4jZzlWofAY/sddefault.webp", "height": 480, "width": 640, "preference": -4, "id": "37", "resolution": "640x480"}, {"url": "https://i.ytimg.com/vi/a4jZzlWofAY/hq720.jpg", "preference": -3, "id": "38"}, {"url": "https://i.ytimg.com/vi_webp/a4jZzlWofAY/hq720.webp", "preference": -2, "id": "39"}, {"url": "https://i.ytimg.com/vi/a4jZzlWofAY/maxresdefault.jpg", "height": 720, "width": 1280, "preference": -1, "id": "40", "resolution": "1280x720"}, {"url": "https://i.ytimg.com/vi_webp/a4jZzlWofAY/maxresdefault.webp", "height": 1080, "width": 1920, "preference": 0, "id": "41", "resolution": "1920x1080"}], "thumbnail": "https://i.ytimg.com/vi_webp/a4jZzlWofAY/maxresdefault.webp", "description": "Shout out to Tacocat.  No, not that #Tacocat, _this_ Tacocat: https://www.youtube.com/watch?v=DhPdDvT3wHk\nSupport the creation of new content on the channel (and speak to me, directly, if you want to) via Patreon, for $1 per month: https://www.patreon.com/a_bas_le_ciel\nWhy are comments disabled on my youtube channel?  Here's the answer, in a relatively uplifting 5 minute video: https://www.youtube.com/watch?v=EHb9k30KTXM\nA searchable list of all of my videos (more effective than searching within youtube, IMO) can be found here: https://aryailia.github.io/a-bas-le-ciel/all.html\nFind me on Instagram: https://www.instagram.com/a_bas_le_ciel/?hl=en\n\u00e0-bas-le-ciel is not my only youtube channel\u2026 there is, in fact, another channel that has my own legal name, Eisel Mazard: https://www.youtube.com/channel/UCuxp5G-XFGcH4lmgejZddqA/videos\n#quitvideogames #boycottnintendo", "upload_date": "20211127", "uploader": "\u00e0-bas-le-ciel", "uploader_id": "HeiJinZhengZhi", "uploader_url": "http://www.youtube.com/user/HeiJinZhengZhi", "channel_id": "UCWPKJM4CT6ES2BrUz9wbELw", "channel_url": "https://www.youtube.com/channel/UCWPKJM4CT6ES2BrUz9wbELw", "duration": 137, "view_count": 1095, "age_limit": 0, "webpage_url": "https://www.youtube.com/watch?v=a4jZzlWofAY", "categories": ["Education"], "playable_in_embed": true, "is_live": false, "was_live": false, "live_status": "not_live", "like_count": 48, "channel": "\u00e0-bas-le-ciel", "availability": "public", "webpage_url_basename": "watch", "extractor": "youtube", "extractor_key": "Youtube", "display_id": "a4jZzlWofAY", "duration_string": "2:17", "format": "247 - 1280x720 (720p)+251 - audio only (medium)", "format_id": "247+251", "ext": "webm", "protocol": "https+https", "language": "", "format_note": "720p+medium", "filesize_approx": 15696261, "tbr": 914.5160000000001, "width": 1280, "height": 720, "resolution": "1280x720", "fps": 30, "dynamic_range": "SDR", "vcodec": "vp9", "vbr": 802.629, "acodec": "opus", "abr": 111.887, "asr": 48000, "fulltitle": "Stop Buying Nintendo Games. Stop Buying Nintendo Consoles. Stop Buying Joy-Cons.", "epoch": 1658260574}